lib_dzne_math/__init__.py
lib_dzne_math/functions/__init__.py
lib_dzne_math/na/__init__.py
lib_dzne_math/numerals/__init__.py
lib_dzne_math/statistics/__init__.py
lib_dzne_math/statistics/plots/DataEntry.py
lib_dzne_math/statistics/plots/__init__.py
lib_dzne_math-0.2.10.dist-info/LICENSE.txt
lib_dzne_math-0.2.10.dist-info/METADATA
lib_dzne_math-0.2.10.dist-info/WHEEL
lib_dzne_math-0.2.10.dist-info/top_level.txt
lib_dzne_math-0.2.10.dist-info/RECORD
