Metadata-Version: 2.1
Name: lib-dzne-math
Version: 0.2.10
Summary: Libary for math.
Author-email: Johannes Programming <johannes-programming@posteo.org>
License: The MIT License (MIT)
Project-URL: Source, https://github.com/johannes-programming/lib_dzne_math
Project-URL: Download, https://pypi.org/project/lib-dzne-math/#files
Classifier: Programming Language :: Python
Classifier: Programming Language :: Python :: 3
Requires-Python: >=3.11
License-File: LICENSE.txt
Requires-Dist: na-quantors >=1.0
Requires-Dist: expit >=0.0.2
Requires-Dist: roman >=4.1
Requires-Dist: openpyxl >=3.1.2
Requires-Dist: simple-pca >=0.1
